pdfdancer/__init__.py
pdfdancer/client_v1.py
pdfdancer/exceptions.py
pdfdancer/models.py
pdfdancer/paragraph_builder.py
pdfdancer_python-0.1.0.dist-info/METADATA
pdfdancer_python-0.1.0.dist-info/WHEEL
pdfdancer_python-0.1.0.dist-info/top_level.txt
pdfdancer_python-0.1.0.dist-info/RECORD
